pyinstaller_gui/__init__.py
pyinstaller_gui/__main__.py
pyinstaller_gui/gui.py
pyinstaller_gui/project_info.py
pyinstaller_gui/pyinstaller_thread.py
pyinstaller_gui/styles.py
pyinstaller_gui-1.0.4.dist-info/LICENSE
pyinstaller_gui-1.0.4.dist-info/METADATA
pyinstaller_gui-1.0.4.dist-info/WHEEL
pyinstaller_gui-1.0.4.dist-info/entry_points.txt
pyinstaller_gui-1.0.4.dist-info/top_level.txt
pyinstaller_gui-1.0.4.dist-info/RECORD
