Metadata-Version: 2.1
Name: pyinstaller-gui
Version: 1.0.4
Summary: A powerful GUI wrapper for PyInstaller — convert your Python scripts into standalone executables for Windows, macOS, and Linux with ease.
Home-page: https://github.com/inject3r/pyinstaller-gui
Author: Abolfazl Hosseini
Author-email: tryuzr@gmail.com
License: MIT
Project-URL: Source Code, https://github.com/inject3r/pyinstaller-gui
Project-URL: Bug Tracker, https://github.com/inject3r/pyinstaller-gui/issues
Keywords: gui,executable,pyinstaller,python,converter,cross-platform,windows,macos,linux,build tool,script to exe,python packaging,application builder,standalone app,no coding,desktop app,code bundler
Classifier: License :: OSI Approved :: MIT License
Classifier: Programming Language :: Python
Classifier: Programming Language :: Python :: 3
Classifier: Programming Language :: Python :: 3.6
Classifier: Programming Language :: Python :: 3.7
Classifier: Programming Language :: Python :: 3.8
Classifier: Programming Language :: Python :: 3.9
Classifier: Programming Language :: Python :: 3.10
Classifier: Programming Language :: Python :: 3.11
Classifier: Programming Language :: Python :: 3.12
Classifier: Programming Language :: Python :: 3.13
Classifier: Operating System :: OS Independent
Requires-Python: >=3.6
License-File: LICENSE
Requires-Dist: PyQt6>=6.8.1
Requires-Dist: pyinstaller>=6.11.1
